{"is_source_file": true, "format": "TypeScript", "description": "This file defines and exports a sample list of recipes, each with properties like id, name, description, image, ingredients, instructions, servings, and reviews. It imports the Recipe type from an external types definition.", "external_files": ["@/lib/types"], "external_methods": [], "published": ["sampleRecipes"], "classes": [], "methods": [], "calls": ["import { Recipe } from \"@/lib/types\""], "search-terms": ["sampleRecipes", "recipes", "TypeScript", "recipes array", "recipe data"], "state": 2, "file_id": 12, "knowledge_revision": 74, "git_revision": "409eac8d8c60c2dc1795b50b932506c35d38d070", "revision_history": [{"26": ""}, {"74": "409eac8d8c60c2dc1795b50b932506c35d38d070"}], "ctags": [{"_type": "tag", "name": "sampleRecipes", "path": "/home/kavia/workspace/code-generation/simple-recipe-explorer-45374-45383/frontend_app/src/data/recipes.ts", "pattern": "/^export const sampleRecipes: Omit<Recipe, 'cookTime'>[] = [$/", "language": "TypeScript", "kind": "constant"}], "hash": "7417351e35cc979824d11b31afad03b9", "format-version": 4, "code-base-name": "frontend_app", "filename": "frontend_app/src/data/recipes.ts"}